[
  {
    "id": "personal-website",
    "title": "web",
    "description": "My personal website built with Next.js, featuring a blog, projects showcase, and about page. Designed with simplicity and performance in mind.",
    "tech": ["Next.js", "TypeScript", "Tailwind CSS", "MDX"],
    "links": {
      "github": "https://github.com/username/website",
      "demo": "https://yourdomain.com"
    },
    "featured": true
  },
  {
    "id": "task-manager",
    "title": "Task Manager",
    "description": "A simple yet powerful task management application with drag-and-drop functionality, labels, and due dates.",
    "tech": ["React", "Node.js", "MongoDB", "Express"],
    "links": {
      "github": "https://github.com/username/task-manager"
    },
    "featured": true
  },
  {
    "id": "weather-app",
    "title": "Weather Dashboard",
    "description": "A clean weather dashboard that shows current conditions and forecasts for multiple locations.",
    "tech": ["Vue.js", "TypeScript", "OpenWeather API"],
    "links": {
      "github": "https://github.com/username/weather-app",
      "demo": "https://weather-demo.vercel.app"
    },
    "featured": false
  }
]
